instapy_chromedriver/__init__.py
instapy_chromedriver/chromedriver_linux64
instapy_chromedriver/chromedriver_mac64
instapy_chromedriver/chromedriver_win32.exe
instapy_chromedriver-2.46.dist-info/LICENSE
instapy_chromedriver-2.46.dist-info/METADATA
instapy_chromedriver-2.46.dist-info/WHEEL
instapy_chromedriver-2.46.dist-info/top_level.txt
instapy_chromedriver-2.46.dist-info/RECORD
