Metadata-Version: 2.1
Name: instapy-chromedriver
Version: 2.46
Summary: chromedriver binaries for instapy
Home-page: https://github.com/InstaPy/instapy-chromedriver
Author: Felix Breuer
Author-email: felix@scriptworld.net
License: UNKNOWN
Keywords: chromedriver cross-platform binaries binary instapy
Platform: UNKNOWN
Classifier: License :: OSI Approved :: Apache Software License
Classifier: Programming Language :: Python
Classifier: Operating System :: OS Independent
